ipyformkit/__init__.py
ipyformkit/auxfuncs.py
ipyformkit/core.py
ipyformkit/custom_widgets.py
ipyformkit/assets/custom_widgets.css
ipyformkit/assets/ipyformkit.css
ipyformkit/assets/tooltip_script.js
ipyformkit-0.3.6.dist-info/licenses/LICENSE
ipyformkit-0.3.6.dist-info/METADATA
ipyformkit-0.3.6.dist-info/WHEEL
ipyformkit-0.3.6.dist-info/top_level.txt
ipyformkit-0.3.6.dist-info/RECORD
