Metadata-Version: 2.4
Name: ipyformkit
Version: 0.3.6
Summary: Easy form creation with ipywidgets in Jupyter
Author: Richard Hoppe
License: MIT License
Project-URL: Homepage, https://github.com/RMHoppe/IpyFormKit
Keywords: widgets,ipywidgets,form,Jupyter
Requires-Python: >=3.7
License-File: LICENSE
Requires-Dist: ipywidgets>=8.0.0
Requires-Dist: traitlets
Requires-Dist: IPython>=7.0.0
Dynamic: license-file
